{
    "projects" : [
        {
            "image" : "images/projects/quiet-hours-poster.jpg",
            "title": "MatnNama",
            "bodyText": "- Developer Portfolio Website made in React\n -  Fully customisable and dynamic, easily change data and images.\n - Dark Mode Support",
            "links": [
                {
                    "text": "SibApp",
                    "href": "https://sibapp.com/applications/MatnNama"
                },
                {
                    "text": "Site",
                    "href": "http://www.matnnama.ir"
                }
            ],
            "tags" : [
                "Swift",
                "FireBase"
            ]
        },
        {
            "image" : "images/projects/quiet-hours-poster.jpg",
            "title": "Namava",
            "bodyText": "- A Cab Sharing web app made using **Django** for **VIT** Students. People can create a new cab or request to join an existing cab.\n - Added User authentication and password reset using **SendGrid**.\n - Deployed on **heroku** using **gunicorn**.",
            "links": [
                {
                    "text": "SibApp",
                    "href": "https://sibapp.com/applications/namava?from=search"
                },
                {
                    "text": "Site",
                    "href": "https://namava.ir"
                }
            ],
            "tags" : [
                "Python",
                "Django",
                "BootStrap",
                "SendGrid",
                "Heroku",
                "Gunicorn",
                "VIT"
            ]
        }
    ]
}